util_walk_sftp.py
walk_ftp.py
walk_sftp.py
walk_sftp-0.0.28.dist-info/LICENSE.txt
walk_sftp-0.0.28.dist-info/METADATA
walk_sftp-0.0.28.dist-info/WHEEL
walk_sftp-0.0.28.dist-info/top_level.txt
walk_sftp-0.0.28.dist-info/RECORD
