Metadata-Version: 2.1
Name: walk-sftp
Version: 0.0.28
Summary: Download SFTP files using a glob to get all files & also keep a log to keep track of processing
Home-page: https://github.com/chrisebell24/walk_sftp
Author: Christopher Bell
Author-email: Chris.E.Bell24@gmail.com
Maintainer: Christopher Bell
Maintainer-email: Chris.E.Bell24@gmail.com
License: UNKNOWN
Platform: UNKNOWN
Classifier: Programming Language :: Python :: 3
Classifier: Programming Language :: Python :: 3.6
Classifier: Programming Language :: Python :: 3.7
Classifier: License :: OSI Approved :: GNU General Public License v2 or later (GPLv2+)
Classifier: Operating System :: OS Independent
Requires-Dist: numpy (>=1.16.1)
Requires-Dist: pysftp (>=0.2.9)
Requires-Dist: paramiko (>=2.7.2)
Provides-Extra: dev
Requires-Dist: pytest (>=3.7) ; extra == 'dev'
